clairvoyance/__init__.py
clairvoyance/__main__.py
clairvoyance/cli.py
clairvoyance/client.py
clairvoyance/config.py
clairvoyance/entities/__init__.py
clairvoyance/entities/context.py
clairvoyance/entities/errors.py
clairvoyance/entities/interfaces.py
clairvoyance/entities/meta.py
clairvoyance/entities/oracle.py
clairvoyance/entities/primitives.py
clairvoyance/graphql.py
clairvoyance/oracle.py
clairvoyance/py.typed
clairvoyance/utils.py
clairvoyance/wordlist.txt
clairvoyance-2.5.5.dist-info/LICENSE
clairvoyance-2.5.5.dist-info/METADATA
clairvoyance-2.5.5.dist-info/WHEEL
clairvoyance-2.5.5.dist-info/entry_points.txt
clairvoyance-2.5.5.dist-info/RECORD
