Metadata-Version: 2.1
Name: Clairvoyance
Version: 2.5.5
Summary: Obtain GraphQL API Schema even if the introspection is not enabled
Home-page: https://github.com/nikitastupin/clairvoyance
License: MIT
Author: Nikita Stupin
Author-email: nikitastupin@protonmail.com
Maintainer: Nikita Stupin
Maintainer-email: nikitastupin@protonmail.com
Requires-Python: >=3.8,<4.0
Classifier: License :: OSI Approved :: MIT License
Classifier: Programming Language :: Python :: 3
Classifier: Programming Language :: Python :: 3.8
Classifier: Programming Language :: Python :: 3.9
Classifier: Programming Language :: Python :: 3.10
Classifier: Programming Language :: Python :: 3.11
Classifier: Programming Language :: Python :: 3.12
Requires-Dist: aiohttp[speedups] (>=3.8.1,<4.0.0)
Requires-Dist: asyncio (>=3.4.3,<4.0.0)
Requires-Dist: rich (>=13.3.1,<14.0.0)
Project-URL: Repository, https://github.com/nikitastupin/clairvoyance
